{
    "1": {
        "content": "今日玩家战力达到150000",
        "cond": 150000,
        "name": "150000",
        "reward_id": 802701
    },
    "3": {
        "content": "今日玩家战力达到250000",
        "cond": 250000,
        "name": "250000",
        "reward_id": 802703
    },
    "2": {
        "content": "今日玩家战力达到200000",
        "cond": 200000,
        "name": "200000",
        "reward_id": 802702
    },
    "5": {
        "content": "今日玩家战力达到350000",
        "cond": 350000,
        "name": "350000",
        "reward_id": 802705
    },
    "4": {
        "content": "今日玩家战力达到300000",
        "cond": 300000,
        "name": "300000",
        "reward_id": 802704
    }
}